ahuiwechat/__init__.py
ahuiwechat/pywechat.py
ahuiwechat-1.0.3.dist-info/LICENSE.txt
ahuiwechat-1.0.3.dist-info/METADATA
ahuiwechat-1.0.3.dist-info/WHEEL
ahuiwechat-1.0.3.dist-info/top_level.txt
ahuiwechat-1.0.3.dist-info/RECORD
