Metadata-Version: 2.1
Name: ahuiwechat
Version: 1.0.3
Summary: 企业微信群机器人消息推送应用
Home-page: https://github.com/ahui
Author: 阿辉
Author-email: ahui6888@126.com
Classifier: Programming Language :: Python :: 3
Classifier: License :: OSI Approved :: MIT License
Classifier: Operating System :: OS Independent
Requires-Python: >=3.6
License-File: LICENSE.txt
Requires-Dist: pandas
Requires-Dist: requests
Requires-Dist: urllib3
Requires-Dist: Pillow
